chatkernelrustak/__init__.py
chatkernelrustak-1.8.dist-info/METADATA
chatkernelrustak-1.8.dist-info/WHEEL
chatkernelrustak-1.8.dist-info/top_level.txt
chatkernelrustak-1.8.dist-info/RECORD
