Metadata-Version: 2.1
Name: chatkernelrustak
Version: 1.8
Summary: Kernel for encrypted chat
Home-page: https://github.com/rustakss/security-chat
Author: rustak
Author-email: admin@rustak.tk
License: UNKNOWN
Platform: UNKNOWN
Classifier: Programming Language :: Python :: 3
Classifier: License :: OSI Approved :: MIT License
Classifier: Operating System :: OS Independent
Requires-Python: >=3.6
